lumigo_log_shipper/__init__.py
lumigo_log_shipper/lumigo_shipper.py
lumigo_log_shipper/models.py
lumigo_log_shipper/utils/__init__.py
lumigo_log_shipper/utils/aws_utils.py
lumigo_log_shipper/utils/consts.py
lumigo_log_shipper/utils/encoder.py
lumigo_log_shipper/utils/firehose_dal.py
lumigo_log_shipper/utils/log.py
lumigo_log_shipper/utils/shipper_utils.py
lumigo_log_shipper/utils/sts.py
lumigo_log_shipper/utils/utils.py
lumigo_log_shipper-1.0.29.dist-info/LICENSE
lumigo_log_shipper-1.0.29.dist-info/METADATA
lumigo_log_shipper-1.0.29.dist-info/WHEEL
lumigo_log_shipper-1.0.29.dist-info/top_level.txt
lumigo_log_shipper-1.0.29.dist-info/RECORD
