Metadata-Version: 2.1
Name: lumigo-log-shipper
Version: 1.0.29
Summary: Ship logs to Lumigo platform
Home-page: https://github.com/lumigo-io/lumigo-python-log-shipper.git
Author: Lumigo LTD (https://lumigo.io)
Author-email: support@lumigo.io
License: UNKNOWN
Platform: UNKNOWN
Classifier: Programming Language :: Python :: 3
Classifier: Operating System :: OS Independent
Requires-Dist: dacite (==1.5.1)
